hs_weighted_arbiter/rtl/weighted_round_robin.v
module weighted_round_robin #(
    parameter REQ_NUM = 8
)(
    input                  clk,
    input                  rst_n, 
    input  [REQ_NUM-1 : 0] reqs,
    output [REQ_NUM-1 : 0] grants
);

localparam ADDR_WD = $clog2(REQ_NUM);

reg [REQ_NUM-1 : 0] mask_r;
reg [ADDR_WD   : 0] weights_r [REQ_NUM-1 : 0]; 
reg [ADDR_WD-1 : 0] grant_idx;

wire [REQ_NUM-1 : 0] masked_reqs     = reqs & mask_r;
wire [REQ_NUM-1 : 0] masked_grants   = masked_reqs & ~(masked_reqs - 1'b1);
wire [REQ_NUM-1 : 0] unmasked_grants = reqs & ~(reqs - 1'b1);
wire [REQ_NUM-1 : 0] grants          = has_maksed_reqs ? masked_grants : unmasked_grants;

wire has_maksed_reqs = |masked_reqs;
wire clean_weignts   = ~(|mask_r);

always @(*) begin
    grant_idx = 'b0;
    for (integer i = 0; i < REQ_NUM; i = i + 1) begin
        if (grants[i]) begin
            grant_idx = i;
        end
    end
end

always @(posedge clk or negedge rst_n) begin
    if (!rst_n) begin
        for (integer i = 0; i < REQ_NUM; i = i + 1) begin
            weights_r[i] <= i + 1;
        end
    end
    else if (has_maksed_reqs) begin
        weights_r[grant_idx] <= weights_r[grant_idx] -1'b1;
    end
    else if (clean_weignts) begin
        for (integer i = 0; i < REQ_NUM; i = i + 1) begin
             weights_r[i] <= i + 1;
         end
    end
end

always @(posedge clk or negedge rst_n) begin
    if (!rst_n) begin
        mask_r <= {REQ_NUM{1'b1}};
    end
    else if (has_maksed_reqs) begin
        mask_r[grant_idx] <= weights_r[grant_idx] != 1;
    end
    else if (clean_weignts) begin
        mask_r <= {REQ_NUM{1'b1}};
    end
end

endmodule

hs_weighted_arbiter/rtl/hs_round_robin.v
module hs_round_robin #(
    parameter REQ_NUM = 8
)(
    input                  clk,
    input                  rst_n,

    input  [REQ_NUM-1 : 0] valid_in,
    input  [REQ_NUM-1 : 0] data_in,
    input  [REQ_NUM-1 : 0] last_in,
    output [REQ_NUM-1 : 0] ready_in,

    output                 valid_out,
    output                 data_out,
    output                 last_out,
    input                  ready_out
);

localparam ADDR_WD =  $clog2(REQ_NUM);

reg  [REQ_NUM-1 : 0] grants_r;
reg  [ADDR_WD-1 : 0] grant_idx;
reg                  lock_r;

wire [REQ_NUM-1 : 0] grants;

wire fire_out  = valid_out && ready_out;
wire has_grant = |grants;

weighted_round_robin #(
    .REQ_NUM(REQ_NUM)
) weighted_round_robin(
    .clk(clk),
    .rst_n(rst_n),
    .reqs(valid_in),
    .grants(grants)
);

always @(posedge clk or negedge rst_n) begin
    if (!rst_n) begin
        lock_r   <= 1'b0;
        grants_r <= 'b0;
    end
    else begin
        if (!lock_r && has_grant) begin
            lock_r   <= 1'b1;
            grants_r <= grants;
        end
        else if (fire_out & last_out) begin
            lock_r   <= 1'b0;
            grants_r <= 'b0;
        end
    end
end

// one hot code to binary code
always @(*) begin
    grant_idx = 'b0;
    for (integer i = 0; i < REQ_NUM; i = i + 1) begin
        if (grants_r[i]) begin
            grant_idx = i;
        end
    end
end

assign ready_in  = {REQ_NUM{ready_out}} & grants_r;
assign valid_out = valid_in[grant_idx] & grants_r[grant_idx];
assign data_out  = data_in[grant_idx];
assign last_out  = last_in[grant_idx] & grants_r[grant_idx];

endmodule

hs_weighted_arbiter/sim/tb_arbiter.v
module tb_arbiter;

localparam REQ_NUM = 8;

reg                  clk;
reg                  rst_n;

reg  [REQ_NUM-1 : 0] valid_in;
reg  [REQ_NUM-1 : 0] data_in;
reg  [REQ_NUM-1 : 0] last_in;
wire [REQ_NUM-1 : 0] ready_in;

wire                 valid_out;
wire                 data_out;
wire                 last_out;
reg                  ready_out;

reg  [3 : 0] counters [REQ_NUM-1 : 0];

wire [REQ_NUM-1 : 0] fire_in, last_fire_in;

assign fire_in      = valid_in & ready_in;
assign last_fire_in = fire_in & last_in;

initial begin
    clk = 0;
    forever begin
        #5;
        clk = ~clk;
    end
end

initial begin
    rst_n = 0;
    #3;
    rst_n = 1;
    #2000;
    $finish;
end

initial begin
    $dumpfile("hs_round_robin.vcd");
    $dumpvars;
end

hs_round_robin #(
    .REQ_NUM(REQ_NUM)
) hs_round_robin(
    .clk(clk),
    .rst_n(rst_n),
    .valid_in(valid_in),
    .data_in(data_in),
    .last_in(last_in),
    .ready_in(ready_in),
    .valid_out(valid_out),
    .data_out(data_out),
    .last_out(last_out),
    .ready_out(ready_out)
);

always @(posedge clk or negedge rst_n) begin
    if (!rst_n) begin
        ready_out <= 'b0;
    end
    else begin
        ready_out <= $random;
    end
end

genvar idx;
generate 
    for (idx = 0; idx < REQ_NUM; idx = idx + 1) begin: inpu
        always @(posedge clk or negedge rst_n) begin
            if (!rst_n) begin
                valid_in[idx] <= 1'b0;
                data_in[idx]  <= 1'b0;
                last_in[idx]  <= 1'b0;
                counters[idx] <=  'b0;
            end
            else begin 
                if (!valid_in[idx] || last_fire_in[idx]) begin
                    valid_in[idx] <= $random;
                    data_in[idx]  <= $random;
                    last_in[idx]  <= 1'b0;
                    counters[idx] <= $random + 1'b1;
                end
                if (fire_in[idx]) begin
                    counters[idx] <= counters[idx] - 1'b1;
                    if (counters[idx] == 1'b1) begin
                        last_in[idx] <= 1'b1;
                    end
                end
            end
        end
    end
endgenerate

endmodule

hs_weighted_arbiter/build/hs_round_robin.vcd
$date
	Sun Oct 02 19:23:32 2022
$end
$version
	Icarus Verilog
$end
$timescale
	1s
$end
$scope module tb_arbiter $end
$var wire 8 ! fire_in [7:0] $end
$var wire 8 " last_fire_in [7:0] $end
$var wire 1 # valid_out $end
$var wire 8 $ ready_in [7:0] $end
$var wire 1 % last_out $end
$var wire 1 & data_out $end
$var parameter 32 ' REQ_NUM $end
$var reg 1 ( clk $end
$var reg 8 ) data_in [7:0] $end
$var reg 8 * last_in [7:0] $end
$var reg 1 + ready_out $end
$var reg 1 , rst_n $end
$var reg 8 - valid_in [7:0] $end
$scope begin inpu[0] $end
$var parameter 2 . idx $end
$upscope $end
$scope begin inpu[1] $end
$var parameter 2 / idx $end
$upscope $end
$scope begin inpu[2] $end
$var parameter 3 0 idx $end
$upscope $end
$scope begin inpu[3] $end
$var parameter 3 1 idx $end
$upscope $end
$scope begin inpu[4] $end
$var parameter 4 2 idx $end
$upscope $end
$scope begin inpu[5] $end
$var parameter 4 3 idx $end
$upscope $end
$scope begin inpu[6] $end
$var parameter 4 4 idx $end
$upscope $end
$scope begin inpu[7] $end
$var parameter 4 5 idx $end
$upscope $end
$scope module hs_round_robin $end
$var wire 1 ( clk $end
$var wire 8 6 data_in [7:0] $end
$var wire 1 7 fire_out $end
$var wire 8 8 last_in [7:0] $end
$var wire 1 % last_out $end
$var wire 8 9 ready_in [7:0] $end
$var wire 1 + ready_out $end
$var wire 1 , rst_n $end
$var wire 8 : valid_in [7:0] $end
$var wire 1 # valid_out $end
$var wire 1 ; has_grant $end
$var wire 8 < grants [7:0] $end
$var wire 1 & data_out $end
$var parameter 32 = ADDR_WD $end
$var parameter 32 > REQ_NUM $end
$var reg 3 ? grant_idx [2:0] $end
$var reg 8 @ grants_r [7:0] $end
$var reg 1 A lock_r $end
$scope module weighted_round_robin $end
$var wire 1 B clean_weignts $end
$var wire 1 ( clk $end
$var wire 8 C masked_grants [7:0] $end
$var wire 8 D masked_reqs [7:0] $end
$var wire 8 E reqs [7:0] $end
$var wire 1 , rst_n $end
$var wire 8 F unmasked_grants [7:0] $end
$var wire 1 G has_maksed_reqs $end
$var wire 8 H grants [7:0] $end
$var parameter 32 I ADDR_WD $end
$var parameter 32 J REQ_NUM $end
$var reg 3 K grant_idx [2:0] $end
$var reg 8 L mask_r [7:0] $end
$scope begin $ivl_for_loop1 $end
$var integer 32 M i [31:0] $end
$upscope $end
$scope begin $ivl_for_loop2 $end
$var integer 32 N i [31:0] $end
$upscope $end
$scope begin $ivl_for_loop3 $end
$var integer 32 O i [31:0] $end
$upscope $end
$upscope $end
$scope begin $ivl_for_loop0 $end
$var integer 32 P i [31:0] $end
$upscope $end
$upscope $end
$upscope $end
$enddefinitions $end
$comment Show the parameter values. $end
$dumpall
b1000 J
b11 I
b1000 >
b11 =
b111 5
b110 4
b101 3
b100 2
b11 1
b10 0
b1 /
b0 .
b1000 '
$end
#0
$dumpvars
b1000 P
bx O
b1000 N
b1000 M
b11111111 L
b0 K
b0 H
0G
b0 F
b0 E
b0 D
b0 C
0B
0A
b0 @
b0 ?
b0 <
0;
b0 :
b0 9
b0 8
07
b0 6
b0 -
0,
x+
b0 *
b0 )
0(
0&
0%
b0 $
0#
b0 "
b0 !
$end
#3
1,
#5
b1 K
b1000 M
1;
b10 <
b10 H
b10 C
1G
b11011110 D
b10 F
0+
b11011110 -
b11011110 :
b11011110 E
1&
b1100011 )
b1100011 6
1(
#10
0(
#15
b1000 M
b0 K
b1 <
b1 H
17
b1 C
1#
b11011111 D
b1 F
b10 !
b1 ?
b1000 P
b10 $
b10 9
b11011111 -
b11011111 :
b11011111 E
b10 @
1A
1+
1(
#20
0(
#25
b1 K
b1000 M
b10 <
b10 H
b10 C
b11011110 D
b11111110 L
b1000011 )
b1000011 6
1(
#30
0(
#35
b1000 M
b10 K
b100 <
b100 H
b100 C
b0 !
b11111100 D
07
b0 $
b0 9
b1100011 )
b1100011 6
b11111111 -
b11111111 :
b11111111 E
b11111100 L
0+
1(
#40
0(
#45
b10 !
17
b10 $
b10 9
1+
1(
#50
0(
#55
1(
#60
0(
#65
b1000 M
b11 K
b1000 <
b1000 H
b0 !
b1000 C
07
b0 $
b0 9
b11111000 D
0+
b11111000 L
1(
#70
0(
#75
1(
#80
0(
#85
b10 !
17
b10 $
b10 9
1+
1(
#90
0(
#95
1(
#100
0(
#105
b1000 M
b100 K
b10000 <
b10000 H
b10000 C
b11110000 D
b11110000 L
1(
#110
0(
#115
b0 !
07
b0 $
b0 9
0+
1(
#120
0(
#125
1(
#130
0(
#135
1(
#140
0(
#145
1(
#150
0(
#155
b1000 M
b101 K
b100000 <
b100000 H
b100000 C
b11100000 D
b11100000 L
1(
#160
0(
#165
b10 !
17
b10 $
b10 9
1+
1(
#170
0(
#175
b0 !
07
b0 $
b0 9
0+
1(
#180
0(
#185
1(
#190
0(
#195
b10 !
17
b10 $
b10 9
1+
1(
#200
0(
#205
1(
#210
0(
#215
b1000 M
b110 K
b1000000 <
b1000000 H
b1000000 C
b0 !
b11000000 D
07
b0 $
b0 9
b11000000 L
0+
1(
#220
0(
#225
1(
#230
0(
#235
1(
#240
0(
#245
1(
#250
0(
#255
1(
#260
0(
#265
b10 !
17
b10 $
b10 9
1+
1(
#270
0(
#275
1(
#280
0(
#285
b1000 M
b111 K
b10000000 <
b10000000 H
b10000000 C
b10000000 D
b10000000 L
1(
#290
0(
#295
1(
#300
0(
#305
1%
b10 "
b10 *
b10 8
1(
#310
0(
#315
b0 "
b0 !
b1000 P
b0 ?
0#
0%
07
b0 $
b0 9
b0 *
b0 8
b11111101 -
b11111101 :
b11111101 E
b0 @
0A
0+
1(
#320
0(
#325
17
1#
b10000000 !
0&
b111 ?
b1000 P
b10000000 $
b10000000 9
1+
b10000000 @
1A
b1100001 )
b1100001 6
b11111111 -
b11111111 :
b11111111 E
1(
#330
0(
#335
1(
#340
0(
#345
b0 !
07
b0 $
b0 9
0+
1(
#350
0(
#355
b10000000 !
17
b10000000 $
b10000000 9
1+
1(
#360
0(
#365
b1000 M
b0 K
b0 C
b1 <
b1 H
1B
0G
b0 D
b0 L
1(
#370
0(
#375
b1000 M
b1 C
1;
b1 <
b1 H
b0 !
0B
1G
b11111111 D
07
b0 $
b0 9
b11111111 L
0+
b1000 O
1(
#380
0(
#385
b1 K
b1000 M
b10 <
b10 H
b10000000 !
b10 C
17
b10000000 $
b10000000 9
b11111110 D
1+
b11111110 L
1(
#390
0(
#395
1(
#400
0(
#405
b1000 M
b10 K
b100 <
b100 H
b100 C
b11111100 D
b11111100 L
1(
#410
0(
#415
b0 !
07
b0 $
b0 9
0+
1(
#420
0(
#425
b10000000 !
17
b10000000 $
b10000000 9
1+
1(
#430
0(
#435
b1000 M
b11 K
b1000 <
b1000 H
b1000 C
b11111000 D
b11111000 L
1(
#440
0(
#445
b0 !
07
b0 $
b0 9
0+
1(
#450
0(
#455
1(
#460
0(
#465
1(
#470
0(
#475
b1000 M
b100 K
b10000 <
b10000 H
b10000 C
b11110000 D
b11110000 L
1(
#480
0(
#485
b10000000 !
17
b10000000 $
b10000000 9
1+
1(
#490
0(
#495
1(
#500
0(
#505
b0 !
07
b0 $
b0 9
0+
1(
#510
0(
#515
1(
#520
0(
#525
b1000 M
b101 K
b100000 <
b100000 H
b10000000 !
b100000 C
17
b10000000 $
b10000000 9
b11100000 D
1+
b11100000 L
1(
#530
0(
#535
1(
#540
0(
#545
1(
#550
0(
#555
1(
#560
0(
#565
1%
b10000000 "
b10000000 *
b10000000 8
1(
#570
0(
#575
b0 !
b0 "
b1000 P
b0 ?
0#
0%
07
b0 $
b0 9
b0 *
b0 8
1&
b11100001 )
b11100001 6
b0 @
0A
0+
1(
#580
0(
#585
b1000 M
b110 K
b1000000 <
b1000000 H
1#
b1000000 C
b101 ?
b1000 P
b11000000 D
b100000 @
1A
b11000000 L
1(
#590
0(
#595
1(
#600
0(
#605
1(
#610
0(
#615
1(
#620
0(
#625
1(
#630
0(
#635
1(
#640
0(
#645
1(
#650
0(
#655
b1000 M
b111 K
b10000000 <
b10000000 H
b10000000 C
b100000 !
b10000000 D
17
b100000 $
b100000 9
b10000000 L
1+
1(
#660
0(
#665
1(
#670
0(
#675
1(
#680
0(
#685
1(
#690
0(
#695
1%
b100000 "
b100000 *
b100000 8
1(
#700
0(
#705
07
b1000 P
b0 ?
b0 $
b0 9
0%
b0 "
0#
b0 !
0+
b0 @
0A
b0 *
b0 8
b11011111 -
b11011111 :
b11011111 E
1(
#710
0(
#715
1#
b111 ?
b1000 P
b11111111 -
b11111111 :
b11111111 E
b10000000 @
1A
1(
#720
0(
#725
b10000000 !
17
b10000000 $
b10000000 9
1+
1(
#730
0(
#735
b1000 M
b0 K
b0 C
b1 <
b1 H
1B
0G
b0 D
b0 L
1(
#740
0(
#745
b1000 M
b1 C
1;
b1 <
b1 H
0B
1G
b11111111 D
b11111111 L
b1000 O
1(
#750
0(
#755
b1 K
b1000 M
b10 <
b10 H
b10 C
b11111110 D
b11111110 L
1(
#760
0(
#765
b0 !
07
b0 $
b0 9
0+
1(
#770
0(
#775
b1000 M
b10 K
b100 <
b100 H
b100 C
b11111100 D
b11111100 L
1(
#780
0(
#785
1(
#790
0(
#795
b10000000 !
17
b10000000 $
b10000000 9
1+
1(
#800
0(
#805
b1000 M
b11 K
b1000 <
b1000 H
b0 !
b1000 C
07
b0 $
b0 9
b11111000 D
0+
b11111000 L
1(
#810
0(
#815
1(
#820
0(
#825
1(
#830
0(
#835
b10000000 !
17
b10000000 $
b10000000 9
1+
1(
#840
0(
#845
b1000 M
b100 K
b10000 <
b10000 H
b10000 C
b11110000 D
b11110000 L
1(
#850
0(
#855
b0 !
07
b0 $
b0 9
0+
1(
#860
0(
#865
1(
#870
0(
#875
b10000000 !
17
b10000000 $
b10000000 9
1+
1(
#880
0(
#885
b0 !
07
b0 $
b0 9
0+
1(
#890
0(
#895
b1000 M
b101 K
b100000 <
b100000 H
b100000 C
b11100000 D
b11100000 L
1(
#900
0(
#905
1(
#910
0(
#915
b10000000 !
17
b10000000 $
b10000000 9
1+
1(
#920
0(
#925
b0 !
07
b0 $
b0 9
0+
1(
#930
0(
#935
1(
#940
0(
#945
b10000000 !
17
b10000000 $
b10000000 9
1+
1(
#950
0(
#955
b1000 M
b110 K
b1000000 <
b1000000 H
b1000000 C
b0 !
b11000000 D
07
b0 $
b0 9
b11000000 L
0+
1(
#960
0(
#965
b10000000 !
17
b10000000 $
b10000000 9
1+
1(
#970
0(
#975
1(
#980
0(
#985
1(
#990
0(
#995
1(
#1000
0(
#1005
1(
#1010
0(
#1015
b0 !
1%
b0 "
07
b0 $
b0 9
b10000000 *
b10000000 8
0+
1(
#1020
0(
#1025
b1000 M
b111 K
b10000000 <
b10000000 H
b10000000 C
b10000000 D
b10000000 L
1(
#1030
0(
#1035
1(
#1040
0(
#1045
b10000000 "
b10000000 !
17
b10000000 $
b10000000 9
1+
1(
#1050
0(
#1055
b1000 M
b0 K
b0 C
b1 <
b1 H
b0 "
0G
b0 D
b0 !
b1000 P
b0 ?
0#
0%
07
b0 $
b0 9
b0 *
b0 8
b1111111 -
b1111111 :
b1111111 E
b0 @
0A
0+
1(
#1060
0(
#1065
b1 !
17
b1000 P
1#
b1 $
b1 9
1+
b1 @
1A
b1100001 )
b1100001 6
1(
#1070
0(
#1075
1(
#1080
0(
#1085
b111 K
b1000 M
b0 !
b10000000 C
1;
b10000000 <
b10000000 H
07
b0 $
b0 9
1G
b10000000 D
0+
b11100001 )
b11100001 6
b11111111 -
b11111111 :
b11111111 E
1(
#1090
0(
#1095
1(
#1100
0(
#1105
b1 !
17
b1 $
b1 9
1+
1(
#1110
0(
#1115
b0 !
07
b0 $
b0 9
0+
1(
#1120
0(
#1125
1(
#1130
0(
#1135
b1000 M
b0 K
b0 C
b1 <
b1 H
b1 !
1B
0G
b0 D
17
b1 $
b1 9
b0 L
1+
1(
#1140
0(
#1145
b1000 M
b0 !
b1 C
1;
b1 <
b1 H
07
b0 $
b0 9
0B
1G
b11111111 D
0+
b11111111 L
b1000 O
1(
#1150
0(
#1155
b1 K
b1000 M
b10 <
b10 H
b10 C
b11111110 D
b11111110 L
1(
#1160
0(
#1165
1(
#1170
0(
#1175
b1000 M
b10 K
b100 <
b100 H
b100 C
b1 !
b11111100 D
17
b1 $
b1 9
b11111100 L
1+
1(
#1180
0(
#1185
b0 !
07
b0 $
b0 9
0+
1(
#1190
0(
#1195
b1 !
17
b1 $
b1 9
1+
1(
#1200
0(
#1205
b1000 M
b11 K
b1000 <
b1000 H
b1000 C
b11111000 D
b11111000 L
1(
#1210
0(
#1215
b0 !
07
b0 $
b0 9
0+
1(
#1220
0(
#1225
1(
#1230
0(
#1235
1(
#1240
0(
#1245
b1000 M
b100 K
b10000 <
b10000 H
b10000 C
b11110000 D
b11110000 L
1(
#1250
0(
#1255
b1 !
17
b1 $
b1 9
1+
1(
#1260
0(
#1265
b0 !
07
b0 $
b0 9
0+
1(
#1270
0(
#1275
1(
#1280
0(
#1285
1(
#1290
0(
#1295
b1000 M
b101 K
b100000 <
b100000 H
b100000 C
b11100000 D
b11100000 L
1(
#1300
0(
#1305
b1 !
17
b1 $
b1 9
1+
1(
#1310
0(
#1315
1(
#1320
0(
#1325
1(
#1330
0(
#1335
b0 !
1%
b0 "
07
b0 $
b0 9
b1 *
b1 8
0+
1(
#1340
0(
#1345
b1 "
b1 !
17
b1 $
b1 9
1+
1(
#1350
0(
#1355
b1000 M
b110 K
b1000000 <
b1000000 H
b1000000 C
07
b0 !
b0 "
b11000000 D
b1000 P
0#
0%
b0 $
b0 9
b0 *
b0 8
0&
b11100000 )
b11100000 6
b11000000 L
b0 @
0A
1(
#1360
0(
#1365
17
1#
b1000000 !
1&
b110 ?
b1000 P
b1000000 $
b1000000 9
b1000000 @
1A
1(
#1370
0(
#1375
1(
#1380
0(
#1385
1(
#1390
0(
#1395
1%
b1000000 "
b1000000 *
b1000000 8
1(
#1400
0(
#1405
07
b0 !
b1000 P
b0 ?
0#
b0 $
b0 9
0%
b0 "
b0 @
0A
b0 *
b0 8
0&
b10100000 )
b10100000 6
1(
#1410
0(
#1415
1#
b110 ?
b1000 P
b1000000 @
1A
0+
1(
#1420
0(
#1425
b1000 M
b111 K
b10000000 <
b10000000 H
b10000000 C
b10000000 D
b10000000 L
1(
#1430
0(
#1435
1(
#1440
0(
#1445
1(
#1450
0(
#1455
b1000000 !
17
b1000000 $
b1000000 9
1+
1(
#1460
0(
#1465
1(
#1470
0(
#1475
b0 !
07
b0 $
b0 9
0+
1(
#1480
0(
#1485
1(
#1490
0(
#1495
b1000000 !
17
b1000000 $
b1000000 9
1+
1(
#1500
0(
#1505
b1000 M
b0 K
b0 !
b0 C
b1 <
b1 H
07
b0 $
b0 9
1B
0G
b0 D
0+
b0 L
1(
#1510
0(
#1515
b1000 M
b1 C
1;
b1 <
b1 H
0B
1G
b11111111 D
b11111111 L
b1000 O
1(
#1520
0(
#1525
b1 K
b1000 M
b10 <
b10 H
b1000000 !
b10 C
17
b1000000 $
b1000000 9
b11111110 D
1+
b11111110 L
1(
#1530
0(
#1535
b0 !
07
b0 $
b0 9
0+
1(
#1540
0(
#1545
b1000 M
b10 K
b100 <
b100 H
b100 C
b11111100 D
b11111100 L
1(
#1550
0(
#1555
b1000000 !
17
b1000000 $
b1000000 9
1+
1(
#1560
0(
#1565
b0 !
07
b0 $
b0 9
0+
1(
#1570
0(
#1575
b1000 M
b11 K
b1000 <
b1000 H
b1000 C
b11111000 D
b11111000 L
1(
#1580
0(
#1585
b1000000 !
17
b1000000 $
b1000000 9
1+
1(
#1590
0(
#1595
1(
#1600
0(
#1605
1(
#1610
0(
#1615
b1000 M
b100 K
b10000 <
b10000 H
b10000 C
b0 !
b11110000 D
07
b0 $
b0 9
b11110000 L
0+
1(
#1620
0(
#1625
1(
#1630
0(
#1635
1(
#1640
0(
#1645
b1000000 !
17
b1000000 $
b1000000 9
1+
1(
#1650
0(
#1655
b0 !
07
b0 $
b0 9
0+
1(
#1660
0(
#1665
b1000 M
b101 K
b100000 <
b100000 H
b100000 C
b11100000 D
b11100000 L
1(
#1670
0(
#1675
b1000000 !
17
b1000000 $
b1000000 9
1+
1(
#1680
0(
#1685
b0 !
07
b0 $
b0 9
0+
1(
#1690
0(
#1695
1(
#1700
0(
#1705
1(
#1710
0(
#1715
1(
#1720
0(
#1725
b1000 M
b110 K
b1000000 <
b1000000 H
b1000000 !
b1000000 C
17
b1000000 $
b1000000 9
b11000000 D
1+
b11000000 L
1(
#1730
0(
#1735
b0 !
07
b0 $
b0 9
0+
1(
#1740
0(
#1745
1(
#1750
0(
#1755
1(
#1760
0(
#1765
b1000000 !
17
b1000000 $
b1000000 9
1+
1(
#1770
0(
#1775
1(
#1780
0(
#1785
b0 !
07
b0 $
b0 9
0+
1(
#1790
0(
#1795
b1000 M
b111 K
b10000000 <
b10000000 H
b10000000 C
b1000000 !
b10000000 D
17
b1000000 $
b1000000 9
b10000000 L
1+
1(
#1800
0(
#1805
1(
#1810
0(
#1815
1%
b1000000 "
b1000000 *
b1000000 8
1(
#1820
0(
#1825
07
b0 !
b1000 P
b0 ?
0#
b0 $
b0 9
0%
b0 "
b0 @
0A
b0 *
b0 8
1(
#1830
0(
#1835
17
1#
b10000000 !
1&
b111 ?
b1000 P
b10000000 $
b10000000 9
b10000000 @
1A
1(
#1840
0(
#1845
b0 !
07
b0 $
b0 9
0+
1(
#1850
0(
#1855
1(
#1860
0(
#1865
b10000000 !
17
b10000000 $
b10000000 9
1+
1(
#1870
0(
#1875
b1000 M
b0 K
b0 C
b1 <
b1 H
b0 !
1B
0G
b0 D
07
b0 $
b0 9
b0 L
0+
1(
#1880
0(
#1885
b1000 M
b1 C
1;
b1 <
b1 H
0B
1G
b11111111 D
b11111111 L
b1000 O
1(
#1890
0(
#1895
b1 K
b1000 M
b10 <
b10 H
b10 C
b10000000 !
b11111110 D
17
b10000000 $
b10000000 9
b11111110 L
1+
1(
#1900
0(
#1905
1(
#1910
0(
#1915
b1000 M
b10 K
b100 <
b100 H
b100 C
b0 !
b11111100 D
07
b0 $
b0 9
b11111100 L
0+
1(
#1920
0(
#1925
1(
#1930
0(
#1935
b10000000 !
17
b10000000 $
b10000000 9
1+
1(
#1940
0(
#1945
b1000 M
b11 K
b1000 <
b1000 H
b0 !
b1000 C
07
b0 $
b0 9
b11111000 D
0+
b11111000 L
1(
#1950
0(
#1955
1(
#1960
0(
#1965
b10000000 !
17
b10000000 $
b10000000 9
1+
1(
#1970
0(
#1975
b0 !
07
b0 $
b0 9
0+
1(
#1980
0(
#1985
b1000 M
b100 K
b10000 <
b10000 H
b10000000 !
b10000 C
17
b10000000 $
b10000000 9
b11110000 D
1+
b11110000 L
1(
