rtl/apb/apb_rx.v
module apb_rx #(
    parameter DATA_BW = 8,
    parameter ADDR_BW = 8
)(
    input                    clk,
    input                    rst_n,
    input                    psel,
    input                    penable,
    input                    pwrite,
    input  [ADDR_BW - 1 : 0] paddr,
    input  [DATA_BW - 1 : 0] pwdata,
    output [DATA_BW - 1 : 0] prdata,
    output                   pready
);
    reg [DATA_BW - 1 : 0] mem [(1<<ADDR_BW) - 1 : 0];

    reg [1 : 0] cur_state;
    reg [1 : 0] next_state;

    localparam IDLE = 2'b00,
               SEL  = 2'b01,
               ACCE = 2'b10;

    assign pready = 1;
    
    always @(posedge clk or negedge rst_n) begin
        if(!rst_n)
            cur_state <= IDLE;
        else
            cur_state <= next_state;
    end

    always @(*) begin
        next_state = IDLE;
        case(cur_state)
            IDLE: next_state = psel ? SEL : IDLE;
            SEL:  next_state = ACCE;
            ACCE: begin
                if(pready)
                    next_state = psel ? SEL : IDLE;
                else
                    next_state = ACCE;
            end
        endcase
    end


    always @(posedge clk or negedge rst_n) begin
        if(pwrite && pready)
            mem[paddr] <= pwdata;
    end

    assign prdata = mem[paddr];

endmodule

rtl/apb/apb_tx.v
module apb_tx #(
    parameter DATA_BW = 8,
    parameter ADDR_BW = 8
)(
    input                          clk,
    input                          rst_n,
    input  [DATA_BW + ADDR_BW : 0] cmd_in,
    input                          cmd_vld,
    input  [DATA_BW - 1 : 0]       prdata,
    input                          pready,
    output                         cmd_rdy,
    output                         psel,
    output                         penable,
    output                         pwrite,
    output [ADDR_BW - 1 : 0]       paddr,
    output [DATA_BW - 1 : 0]       pwdata,
    output [DATA_BW - 1 : 0]       read_data,
    output                         read_vld
);

    reg [DATA_BW + ADDR_BW : 0] cmd_in_r;

    reg [1 : 0] cur_state;
    reg [1 : 0] next_state;

    reg [DATA_BW - 1 : 0] read_data_r;

    reg  psel_r;
    reg  penable_r;
    reg  cmd_rdy_r;
    reg  read_vld_r;

    wire cmd_fire = cmd_vld && cmd_rdy;

    localparam IDLE = 2'b00,
               SEL  = 2'b01,
               ACCE = 2'b10;
    
    assign pwdata    = cmd_in_r[DATA_BW - 1 : 0];
    assign paddr     = cmd_in_r[DATA_BW + ADDR_BW - 1 : DATA_BW];
    assign pwrite    = cmd_in_r[DATA_BW + ADDR_BW];

    assign psel      = psel_r;
    assign penable   = penable_r;
    assign cmd_rdy   = cmd_rdy_r;
    assign read_vld  = read_vld_r;
    assign read_data = read_data_r;

    always @(posedge clk or negedge rst_n) begin
        if(!rst_n)
            cur_state <= 'b0;
        else
            cur_state <= next_state;
    end

    always @(*) begin
        next_state = IDLE;
        case(cur_state)
            IDLE: next_state = cmd_fire ? SEL : IDLE;
            SEL:  next_state = ACCE;
            ACCE: next_state = pready ? IDLE : ACCE;
        endcase
    end

    always @(*) begin
        psel_r     = 0;
        penable_r  = 0;
        cmd_rdy_r  = 0;
        read_vld_r = 0;
        case (cur_state)
            IDLE: cmd_rdy_r = 1;
            SEL:  psel_r    = 1;  
            ACCE: begin
                psel_r    = 1;
                penable_r = 1;
                if(!pwrite && pready)
                    read_vld_r = 1;
            end
        endcase
    end
    
    always @(posedge clk or negedge rst_n) begin
        if(!rst_n)
            cmd_in_r <= 'b0;
        else if (cmd_fire) begin
            cmd_in_r <= cmd_in;
        end
    end
        
    /********************************************* woudl delay a clk
    always @(posedge clk or negedge rst_n) begin
        if (!rst_n) begin
            {pwrite_r, paddr_r, pwdata_r} <= 'b0;
        end
        else if(cmd_fire)
            {pwrite_r, paddr_r, pwdata_r} <= cmd_in_r;
    end   
    **************************************************/
    
    always @(posedge clk or negedge rst_n) begin
        if(!rst_n)
            read_data_r <= 'b0;
        else if(!pwrite)
            read_data_r <= prdata;
    end
    
endmodule

rtl/apb/tb_apb.v
module tb_apb;

    localparam DATA_BW = 4,
               ADDR_BW = 4;
               
    reg                          clk;
    reg                          rst_n;
    reg  [DATA_BW + ADDR_BW : 0] cmd_in;
    reg                          cmd_vld;
    wire  [DATA_BW - 1 : 0]      prdata;
    wire                         pready;
    wire                         cmd_rdy;
    wire                         psel;
    wire                         penable;
    wire                         pwrite;
    wire [ADDR_BW - 1 : 0]       paddr;
    wire [DATA_BW - 1 : 0]       pwdata;
    wire [DATA_BW - 1 : 0]       read_data;
    wire                         read_vld;

    reg [4 : 0] cnt;
    
    wire cmd_fire = cmd_rdy && cmd_vld;
    


    initial begin
        $dumpfile("apb.vcd");
        $dumpvars;
    end

    initial begin
        clk = 0;
        forever begin
            #5;
            clk = ~clk;
        end
    end

    initial begin
        rst_n = 0;
        #3;
        rst_n = 1;
        #1000;
        $finish;
    end

    always @(posedge clk or negedge rst_n) begin
        if(!rst_n)
            cnt <= 'b0;
        else if(cmd_fire)
            cnt <= cnt + 1;
    end

    always @(posedge clk or negedge rst_n) begin
        if(!rst_n) begin 
            cmd_vld <= 0;
            cmd_in  <= 'b0;
        end
        else begin
            cmd_vld <= 1;
            cmd_in  <= {~cnt[4],cnt[3:0],cnt[3:0]};
        end
    end
    

    apb_tx #(
        .DATA_BW(DATA_BW),
        .ADDR_BW(ADDR_BW)
    ) apb_tx(
        .clk(clk),
        .rst_n(rst_n),
        .cmd_in(cmd_in),
        .cmd_rdy(cmd_rdy),
        .cmd_vld(cmd_vld),
        .read_vld(read_vld),
        .read_data(read_data),
        .psel(psel),
        .penable(penable),
        .pwrite(pwrite),
        .paddr(paddr),
        .pwdata(pwdata),
        .prdata(prdata),
        .pready(pready)
    );

    apb_rx #(
        .DATA_BW(DATA_BW),
        .ADDR_BW(ADDR_BW)
    ) apb_rx(
        .clk(clk),
        .rst_n(rst_n),
        .psel(psel),
        .penable(penable),
        .pwrite(pwrite),
        .paddr(paddr),
        .pwdata(pwdata),
        .prdata(prdata),
        .pready(pready)
    );

endmodule

rtl/apb/apb.vcd
$date
	Wed Aug 24 17:31:03 2022
$end
$version
	Icarus Verilog
$end
$timescale
	1s
$end
$scope module tb_apb $end
$var wire 1 ! cmd_fire $end
$var wire 1 " pready $end
$var wire 1 # read_vld $end
$var wire 4 $ read_data [3:0] $end
$var wire 1 % pwrite $end
$var wire 4 & pwdata [3:0] $end
$var wire 1 ' psel $end
$var wire 4 ( prdata [3:0] $end
$var wire 1 ) penable $end
$var wire 4 * paddr [3:0] $end
$var wire 1 + cmd_rdy $end
$var parameter 32 , ADDR_BW $end
$var parameter 32 - DATA_BW $end
$var reg 1 . clk $end
$var reg 9 / cmd_in [8:0] $end
$var reg 1 0 cmd_vld $end
$var reg 5 1 cnt [4:0] $end
$var reg 1 2 rst_n $end
$scope module apb_rx $end
$var wire 1 . clk $end
$var wire 4 3 prdata [3:0] $end
$var wire 1 " pready $end
$var wire 1 2 rst_n $end
$var wire 1 % pwrite $end
$var wire 4 4 pwdata [3:0] $end
$var wire 1 ' psel $end
$var wire 1 ) penable $end
$var wire 4 5 paddr [3:0] $end
$var parameter 2 6 ACCE $end
$var parameter 32 7 ADDR_BW $end
$var parameter 32 8 DATA_BW $end
$var parameter 2 9 IDLE $end
$var parameter 2 : SEL $end
$var reg 2 ; cur_state [1:0] $end
$var reg 2 < next_state [1:0] $end
$upscope $end
$scope module apb_tx $end
$var wire 1 . clk $end
$var wire 1 = cmd_fire $end
$var wire 9 > cmd_in [8:0] $end
$var wire 1 0 cmd_vld $end
$var wire 1 ) penable $end
$var wire 4 ? prdata [3:0] $end
$var wire 1 " pready $end
$var wire 1 ' psel $end
$var wire 4 @ read_data [3:0] $end
$var wire 1 # read_vld $end
$var wire 1 2 rst_n $end
$var wire 1 % pwrite $end
$var wire 4 A pwdata [3:0] $end
$var wire 4 B paddr [3:0] $end
$var wire 1 + cmd_rdy $end
$var parameter 2 C ACCE $end
$var parameter 32 D ADDR_BW $end
$var parameter 32 E DATA_BW $end
$var parameter 2 F IDLE $end
$var parameter 2 G SEL $end
$var reg 9 H cmd_in_r [8:0] $end
$var reg 1 + cmd_rdy_r $end
$var reg 2 I cur_state [1:0] $end
$var reg 2 J next_state [1:0] $end
$var reg 1 K penable_r $end
$var reg 1 L psel_r $end
$var reg 4 M read_data_r [3:0] $end
$var reg 1 N read_vld_r $end
$upscope $end
$upscope $end
$enddefinitions $end
$comment Show the parameter values. $end
$dumpall
b1 G
b0 F
b100 E
b100 D
b10 C
b1 :
b0 9
b100 8
b100 7
b10 6
b100 -
b100 ,
$end
#0
$dumpvars
0N
b0 M
0L
0K
b0x J
b0 I
b0 H
b0 B
b0 A
b0 @
bx ?
bx >
x=
b0 <
b0 ;
b0 5
b0 4
bx 3
02
bx 1
x0
bx /
0.
1+
b0 *
0)
bx (
0'
b0 &
0%
b0 $
0#
1"
x!
$end
#3
12
#5
0=
0!
0+
b0 J
10
bx $
bx @
bx M
b0x I
1.
#10
0.
#15
b1 J
1=
1!
1+
b0 I
1.
#20
0.
#25
b1 <
0=
0!
bx &
bx 4
bx A
bx *
bx 5
bx B
x%
1'
1L
0+
b10 J
bx H
b1 I
1.
#30
0.
#35
1)
1K
1'
1L
b0 J
b10 <
b10 I
b1 ;
1.
#40
0.
#45
b1 J
1=
1!
b0 <
1+
0)
0K
0'
0L
b10 ;
b0 I
1.
#50
0.
#55
b1 <
0=
0!
1'
1L
0+
b10 J
b1 I
b0 ;
1.
#60
0.
#65
b10 <
1)
1K
1'
1L
b0 J
b1 ;
b10 I
1.
#70
0.
#75
b1 J
1=
1!
1+
0)
0K
0'
0L
b0 <
b0 I
b10 ;
1.
#80
0.
#85
0=
0!
b1 <
1'
1L
0+
b10 J
b0 ;
b1 I
1.
#90
0.
#95
1)
1K
1'
1L
b0 J
b10 <
b10 I
b1 ;
1.
#100
0.
#105
b1 J
1=
1!
b0 <
1+
0)
0K
0'
0L
b10 ;
b0 I
1.
#110
0.
#115
b1 <
0=
0!
1'
1L
0+
b10 J
b1 I
b0 ;
1.
#120
0.
#125
b10 <
1)
1K
1'
1L
b0 J
b1 ;
b10 I
1.
#130
0.
#135
b1 J
1=
1!
1+
0)
0K
0'
0L
b0 <
b0 I
b10 ;
1.
#140
0.
#145
0=
0!
b1 <
1'
1L
0+
b10 J
b0 ;
b1 I
1.
#150
0.
#155
1)
1K
1'
1L
b0 J
b10 <
b10 I
b1 ;
1.
#160
0.
#165
b1 J
1=
1!
b0 <
1+
0)
0K
0'
0L
b10 ;
b0 I
1.
#170
0.
#175
b1 <
0=
0!
1'
1L
0+
b10 J
b1 I
b0 ;
1.
#180
0.
#185
b10 <
1)
1K
1'
1L
b0 J
b1 ;
b10 I
1.
#190
0.
#195
b1 J
1=
1!
1+
0)
0K
0'
0L
b0 <
b0 I
b10 ;
1.
#200
0.
#205
0=
0!
b1 <
1'
1L
0+
b10 J
b0 ;
b1 I
1.
#210
0.
#215
1)
1K
1'
1L
b0 J
b10 <
b10 I
b1 ;
1.
#220
0.
#225
b1 J
1=
1!
b0 <
1+
0)
0K
0'
0L
b10 ;
b0 I
1.
#230
0.
#235
b1 <
0=
0!
1'
1L
0+
b10 J
b1 I
b0 ;
1.
#240
0.
#245
b10 <
1)
1K
1'
1L
b0 J
b1 ;
b10 I
1.
#250
0.
#255
b1 J
1=
1!
1+
0)
0K
0'
0L
b0 <
b0 I
b10 ;
1.
#260
0.
#265
0=
0!
b1 <
1'
1L
0+
b10 J
b0 ;
b1 I
1.
#270
0.
#275
1)
1K
1'
1L
b0 J
b10 <
b10 I
b1 ;
1.
#280
0.
#285
b1 J
1=
1!
b0 <
1+
0)
0K
0'
0L
b10 ;
b0 I
1.
#290
0.
#295
b1 <
0=
0!
1'
1L
0+
b10 J
b1 I
b0 ;
1.
#300
0.
#305
b10 <
1)
1K
1'
1L
b0 J
b1 ;
b10 I
1.
#310
0.
#315
b1 J
1=
1!
1+
0)
0K
0'
0L
b0 <
b0 I
b10 ;
1.
#320
0.
#325
0=
0!
b1 <
1'
1L
0+
b10 J
b0 ;
b1 I
1.
#330
0.
#335
1)
1K
1'
1L
b0 J
b10 <
b10 I
b1 ;
1.
#340
0.
#345
b1 J
1=
1!
b0 <
1+
0)
0K
0'
0L
b10 ;
b0 I
1.
#350
0.
#355
b1 <
0=
0!
1'
1L
0+
b10 J
b1 I
b0 ;
1.
#360
0.
#365
b10 <
1)
1K
1'
1L
b0 J
b1 ;
b10 I
1.
#370
0.
#375
b1 J
1=
1!
1+
0)
0K
0'
0L
b0 <
b0 I
b10 ;
1.
#380
0.
#385
0=
0!
b1 <
1'
1L
0+
b10 J
b0 ;
b1 I
1.
#390
0.
#395
1)
1K
1'
1L
b0 J
b10 <
b10 I
b1 ;
1.
#400
0.
#405
b1 J
1=
1!
b0 <
1+
0)
0K
0'
0L
b10 ;
b0 I
1.
#410
0.
#415
b1 <
0=
0!
1'
1L
0+
b10 J
b1 I
b0 ;
1.
#420
0.
#425
b10 <
1)
1K
1'
1L
b0 J
b1 ;
b10 I
1.
#430
0.
#435
b1 J
1=
1!
1+
0)
0K
0'
0L
b0 <
b0 I
b10 ;
1.
#440
0.
#445
0=
0!
b1 <
1'
1L
0+
b10 J
b0 ;
b1 I
1.
#450
0.
#455
1)
1K
1'
1L
b0 J
b10 <
b10 I
b1 ;
1.
#460
0.
#465
b1 J
1=
1!
b0 <
1+
0)
0K
0'
0L
b10 ;
b0 I
1.
#470
0.
#475
b1 <
0=
0!
1'
1L
0+
b10 J
b1 I
b0 ;
1.
#480
0.
#485
b10 <
1)
1K
1'
1L
b0 J
b1 ;
b10 I
1.
#490
0.
#495
b1 J
1=
1!
1+
0)
0K
0'
0L
b0 <
b0 I
b10 ;
1.
#500
0.
#505
0=
0!
b1 <
1'
1L
0+
b10 J
b0 ;
b1 I
1.
#510
0.
#515
1)
1K
1'
1L
b0 J
b10 <
b10 I
b1 ;
1.
#520
0.
#525
b1 J
1=
1!
b0 <
1+
0)
0K
0'
0L
b10 ;
b0 I
1.
#530
0.
#535
b1 <
0=
0!
1'
1L
0+
b10 J
b1 I
b0 ;
1.
#540
0.
#545
b10 <
1)
1K
1'
1L
b0 J
b1 ;
b10 I
1.
#550
0.
#555
b1 J
1=
1!
1+
0)
0K
0'
0L
b0 <
b0 I
b10 ;
1.
#560
0.
#565
0=
0!
b1 <
1'
1L
0+
b10 J
b0 ;
b1 I
1.
#570
0.
#575
1)
1K
1'
1L
b0 J
b10 <
b10 I
b1 ;
1.
#580
0.
#585
b1 J
1=
1!
b0 <
1+
0)
0K
0'
0L
b10 ;
b0 I
1.
#590
0.
#595
b1 <
0=
0!
1'
1L
0+
b10 J
b1 I
b0 ;
1.
#600
0.
#605
b10 <
1)
1K
1'
1L
b0 J
b1 ;
b10 I
1.
#610
0.
#615
b1 J
1=
1!
1+
0)
0K
0'
0L
b0 <
b0 I
b10 ;
1.
#620
0.
#625
0=
0!
b1 <
1'
1L
0+
b10 J
b0 ;
b1 I
1.
#630
0.
#635
1)
1K
1'
1L
b0 J
b10 <
b10 I
b1 ;
1.
#640
0.
#645
b1 J
1=
1!
b0 <
1+
0)
0K
0'
0L
b10 ;
b0 I
1.
#650
0.
#655
b1 <
0=
0!
1'
1L
0+
b10 J
b1 I
b0 ;
1.
#660
0.
#665
b10 <
1)
1K
1'
1L
b0 J
b1 ;
b10 I
1.
#670
0.
#675
b1 J
1=
1!
1+
0)
0K
0'
0L
b0 <
b0 I
b10 ;
1.
#680
0.
#685
0=
0!
b1 <
1'
1L
0+
b10 J
b0 ;
b1 I
1.
#690
0.
#695
1)
1K
1'
1L
b0 J
b10 <
b10 I
b1 ;
1.
#700
0.
#705
b1 J
1=
1!
b0 <
1+
0)
0K
0'
0L
b10 ;
b0 I
1.
#710
0.
#715
b1 <
0=
0!
1'
1L
0+
b10 J
b1 I
b0 ;
1.
#720
0.
#725
b10 <
1)
1K
1'
1L
b0 J
b1 ;
b10 I
1.
#730
0.
#735
b1 J
1=
1!
1+
0)
0K
0'
0L
b0 <
b0 I
b10 ;
1.
#740
0.
#745
0=
0!
b1 <
1'
1L
0+
b10 J
b0 ;
b1 I
1.
#750
0.
#755
1)
1K
1'
1L
b0 J
b10 <
b10 I
b1 ;
1.
#760
0.
#765
b1 J
1=
1!
b0 <
1+
0)
0K
0'
0L
b10 ;
b0 I
1.
#770
0.
#775
b1 <
0=
0!
1'
1L
0+
b10 J
b1 I
b0 ;
1.
#780
0.
#785
b10 <
1)
1K
1'
1L
b0 J
b1 ;
b10 I
1.
#790
0.
#795
b1 J
1=
1!
1+
0)
0K
0'
0L
b0 <
b0 I
b10 ;
1.
#800
0.
#805
0=
0!
b1 <
1'
1L
0+
b10 J
b0 ;
b1 I
1.
#810
0.
#815
1)
1K
1'
1L
b0 J
b10 <
b10 I
b1 ;
1.
#820
0.
#825
b1 J
1=
1!
b0 <
1+
0)
0K
0'
0L
b10 ;
b0 I
1.
#830
0.
#835
b1 <
0=
0!
1'
1L
0+
b10 J
b1 I
b0 ;
1.
#840
0.
#845
b10 <
1)
1K
1'
1L
b0 J
b1 ;
b10 I
1.
#850
0.
#855
b1 J
1=
1!
1+
0)
0K
0'
0L
b0 <
b0 I
b10 ;
1.
#860
0.
#865
0=
0!
b1 <
1'
1L
0+
b10 J
b0 ;
b1 I
1.
#870
0.
#875
1)
1K
1'
1L
b0 J
b10 <
b10 I
b1 ;
1.
#880
0.
#885
b1 J
1=
1!
b0 <
1+
0)
0K
0'
0L
b10 ;
b0 I
1.
#890
0.
#895
b1 <
0=
0!
1'
1L
0+
b10 J
b1 I
b0 ;
1.
#900
0.
#905
b10 <
1)
1K
1'
1L
b0 J
b1 ;
b10 I
1.
#910
0.
#915
b1 J
1=
1!
1+
0)
0K
0'
0L
b0 <
b0 I
b10 ;
1.
#920
0.
#925
0=
0!
b1 <
1'
1L
0+
b10 J
b0 ;
b1 I
1.
#930
0.
#935
1)
1K
1'
1L
b0 J
b10 <
b10 I
b1 ;
1.
#940
0.
#945
b1 J
1=
1!
b0 <
1+
0)
0K
0'
0L
b10 ;
b0 I
1.
#950
0.
#955
b1 <
0=
0!
1'
1L
0+
b10 J
b1 I
b0 ;
1.
#960
0.
#965
b10 <
1)
1K
1'
1L
b0 J
b1 ;
b10 I
1.
#970
0.
#975
b1 J
1=
1!
1+
0)
0K
0'
0L
b0 <
b0 I
b10 ;
1.
#980
0.
#985
0=
0!
b1 <
1'
1L
0+
b10 J
b0 ;
b1 I
1.
#990
0.
#995
1)
1K
1'
1L
b0 J
b10 <
b10 I
b1 ;
1.
