asyb_fifo/rtl/asyn_cmp.v
module asyn_cmp #(
    parameter ADDR_WD = 4
)(
    input  [ADDR_WD-1 : 0] rptr,
    input  [ADDR_WD-1 : 0] wptr,
    input                  wrst_n,
    output                 afull_n,
    output                 aempty_n
);

reg  dir_r;
wire set_n, rst_n;

assign set_n = ~((wptr[ADDR_WD-1] ^ rptr[ADDR_WD-2]) && (wptr[ADDR_WD-2] ~^ rptr[ADDR_WD-1]));
assign rst_n = ~(!wrst_n | ((wptr[ADDR_WD-1] ~^ rptr[ADDR_WD-2]) && (wptr[ADDR_WD-2] ^ rptr[ADDR_WD-1])));

always @(negedge rst_n or negedge set_n) begin
    if (!rst_n) begin
        dir_r <= 1'b0;
    end
    else if (!set_n) begin
        dir_r <= 1'b1;
    end
end

assign afull_n  = ~(dir_r  && (rptr == wptr));
assign aempty_n = ~(~dir_r && (rptr == wptr));

endmodule

asyb_fifo/rtl/rptr_empty.v
module rptr_empty #(
    parameter ADDR_WD = 4
)(
    input                  rclk,
    input                  rrst_n,
    input                  rinc,
    input                  aempty_n,
    output                 rempty,
    output [ADDR_WD-1 : 0] rptr
);

reg  [ADDR_WD-1 : 0] rbin_r, rgray_r;
reg                  rq1_r,  rq2_r;
wire [ADDR_WD-1 : 0] rbnext, rgnext;

assign rbnext = rbin_r + (rinc && !rempty);
assign rgnext = (rbnext >> 1) ^ rbnext;
assign rptr   =  rgray_r;

always @(posedge rclk or negedge rrst_n) begin
    if (!rrst_n) begin
        {rbin_r, rgray_r} <= 'b0;
    end
    else begin
        {rbin_r, rgray_r} <= {rbnext, rgnext};
    end
end

always @ (posedge rclk or negedge rrst_n or negedge aempty_n) begin
    if (!rrst_n) begin
        {rq1_r, rq2_r} <= 'b0;
    end
    else if (!aempty_n) begin
        {rq1_r, rq2_r} <= 2'b11;
    end
    else begin
        {rq1_r, rq2_r} <= {~aempty_n, rq1_r};
    end
end

assign rempty = rq2_r;

endmodule

asyn_fifo/rtl/wptr_full.v
module wptr_full #(
    parameter ADDR_WD = 4
)(
    input                  wclk,
    input                  wrst_n,
    input                  winc,
    input                  afull_n,
    output                 wfull,
    output [ADDR_WD-1 : 0] wptr
);

reg  [ADDR_WD-1 : 0] wbin_r, wgray_r;
reg                  wq1_r,  wq2_r;
wire [ADDR_WD-1 : 0] wbnext, wgnext;

assign wbnext = wbin_r + (winc && !wfull);
assign wgnext = (wbnext >> 1) ^ wbnext;
assign wptr   =  wgray_r;

always @(posedge wclk or negedge wrst_n) begin
    if (!wrst_n) begin
        {wbin_r, wgray_r} <= 'b0;
    end
    else begin
        {wbin_r, wgray_r} <= {wbnext, wgnext};
    end
end

always @ (posedge wclk or negedge wrst_n or negedge afull_n) begin
    if (!wrst_n) begin
        {wq1_r, wq2_r} <= 'b0;
    end
    else if (!afull_n) begin
        {wq1_r, wq2_r} <= 2'b11;
    end
    else begin
        {wq1_r, wq2_r} <= {~afull_n, wq1_r};
    end
end

assign wfull = wq2_r;

endmodule

asyb_fifo/rtl/mem.v
module mem #(
    parameter DATA_WD = 8,
    parameter ADDR_WD = 4
)(
    input                  wclk,
    input                  winc,
    input                  wfull,
    input  [DATA_WD-1 : 0] wdata,
    input  [ADDR_WD-1 : 0] waddr,
    input  [ADDR_WD-1 : 0] raddr,
    output [DATA_WD-1 : 0] rdata             
);

localparam DEPTH = 1 << ADDR_WD;

reg [DATA_WD-1 : 0] mem [DEPTH-1 : 0];

always @(posedge wclk) begin
    if (winc && !wfull) begin
        mem[waddr] <= wdata;
    end
end

assign rdata = mem[raddr];

endmodule

asyb_fifo/rtl/asyn_fifo_top.v
module asyn_fifo_top #(
    parameter DATA_WD = 8,
    parameter ADDR_WD = 4
)(
    input                  wclk,
    input                  wrst_n,
    input                  winc,
    input  [DATA_WD-1 : 0] wdata,
    output                 wfull,

    input                  rclk,
    input                  rrst_n,
    input                  rinc,
    output                 rempty,
    output [DATA_WD-1 : 0] rdata             
);

wire [ADDR_WD-1 : 0] wptr,    rptr;
wire                 afull_n, aempty_n;

mem #(
    .ADDR_WD(ADDR_WD),
    .DATA_WD(DATA_WD)
) mem(
    .wclk(wclk),
    .winc(winc),
    .wfull(wfull),
    .wdata(wdata),
    .rdata(rdata),
    .waddr(wptr),
    .raddr(rptr)
);

wptr_full #(
    .ADDR_WD(ADDR_WD)
) wptr_full(
    .wclk(wclk),
    .winc(winc),
    .wfull(wfull),
    .wrst_n(wrst_n),
    .afull_n(afull_n),
    .wptr(wptr)
);

rptr_empty #(
    .ADDR_WD(ADDR_WD)
) rptr_empty(
    .rclk(rclk),
    .rinc(rinc),
    .rempty(rempty),
    .rrst_n(rrst_n),
    .aempty_n(aempty_n),
    .rptr(rptr)
);

asyn_cmp #(
    .ADDR_WD(ADDR_WD)
) asyn_cmp(
    .rptr(rptr),
    .wptr(wptr),
    .wrst_n(wrst_n),
    .afull_n(afull_n),
    .aempty_n(aempty_n)
);

endmodule

asyn_fifo/sim/tb_asyn_fifo.v
module tb_asyn_fifo;

parameter DATA_WD = 8;
parameter ADDR_WD = 4;

reg                  wclk;
reg                  wrst_n;
reg                  winc;
reg  [DATA_WD-1 : 0] wdata;
wire                 wfull;

reg                  rclk;
reg                  rrst_n;
reg                  rinc;
wire                 rempty;
wire [DATA_WD-1 : 0] rdata;

initial begin
    $dumpfile("asyn_fifo.vcd");
    $dumpvars;
end

initial begin
    wclk = 1'b0;
    forever begin
        #3;
        wclk = ~wclk;
    end
end

initial begin
    rclk = 1'b0;
    forever begin
        #6;
        rclk = ~rclk;
    end
end

initial begin
    winc   = 1'b1;
    rinc   = 1'b1;
    wrst_n = 1'b0;
    rrst_n = 1'b0;
    #2;
    wrst_n = 1'b1;
    rrst_n = 1'b1;
    #400;
    $finish;
end

always #5 begin
    wdata = {$random} % 128;
end

asyn_fifo_top #(
    .ADDR_WD(ADDR_WD),
    .DATA_WD(DATA_WD)
) asyn_fifo_top(
    .wclk(wclk),
    .wrst_n(wrst_n),
    .winc(winc),
    .wfull(wfull),
    .wdata(wdata),
    .rclk(rclk),
    .rrst_n(rrst_n),
    .rinc(rinc),
    .rdata(rdata),
    .rempty(rempty)
);

endmodule

asyb_fifo/build/asyn_fifo.vcd
$date
	Sun Oct 09 21:19:39 2022
$end
$version
	Icarus Verilog
$end
$timescale
	1s
$end
$scope module tb_asyn_fifo $end
$var wire 1 ! wfull $end
$var wire 1 " rempty $end
$var wire 8 # rdata [7:0] $end
$var parameter 32 $ ADDR_WD $end
$var parameter 32 % DATA_WD $end
$var reg 1 & rclk $end
$var reg 1 ' rinc $end
$var reg 1 ( rrst_n $end
$var reg 1 ) wclk $end
$var reg 8 * wdata [7:0] $end
$var reg 1 + winc $end
$var reg 1 , wrst_n $end
$scope module asyn_fifo_top $end
$var wire 1 & rclk $end
$var wire 1 ' rinc $end
$var wire 1 ( rrst_n $end
$var wire 1 ) wclk $end
$var wire 8 - wdata [7:0] $end
$var wire 1 + winc $end
$var wire 1 , wrst_n $end
$var wire 4 . wptr [3:0] $end
$var wire 1 ! wfull $end
$var wire 4 / rptr [3:0] $end
$var wire 1 " rempty $end
$var wire 8 0 rdata [7:0] $end
$var wire 1 1 afull_n $end
$var wire 1 2 aempty_n $end
$var parameter 32 3 ADDR_WD $end
$var parameter 32 4 DATA_WD $end
$scope module asyn_cmp $end
$var wire 1 2 aempty_n $end
$var wire 1 1 afull_n $end
$var wire 1 5 rst_n $end
$var wire 1 6 set_n $end
$var wire 1 , wrst_n $end
$var wire 4 7 wptr [3:0] $end
$var wire 4 8 rptr [3:0] $end
$var parameter 32 9 ADDR_WD $end
$var reg 1 : dir_r $end
$upscope $end
$scope module mem $end
$var wire 8 ; rdata [7:0] $end
$var wire 1 ) wclk $end
$var wire 8 < wdata [7:0] $end
$var wire 1 + winc $end
$var wire 1 ! wfull $end
$var wire 4 = waddr [3:0] $end
$var wire 4 > raddr [3:0] $end
$var parameter 32 ? ADDR_WD $end
$var parameter 32 @ DATA_WD $end
$var parameter 36 A DEPTH $end
$upscope $end
$scope module rptr_empty $end
$var wire 1 2 aempty_n $end
$var wire 1 & rclk $end
$var wire 4 B rgnext [3:0] $end
$var wire 1 ' rinc $end
$var wire 4 C rptr [3:0] $end
$var wire 1 ( rrst_n $end
$var wire 1 " rempty $end
$var wire 4 D rbnext [3:0] $end
$var parameter 32 E ADDR_WD $end
$var reg 4 F rbin_r [3:0] $end
$var reg 4 G rgray_r [3:0] $end
$var reg 1 H rq1_r $end
$var reg 1 " rq2_r $end
$upscope $end
$scope module wptr_full $end
$var wire 1 1 afull_n $end
$var wire 1 ) wclk $end
$var wire 4 I wgnext [3:0] $end
$var wire 1 + winc $end
$var wire 4 J wptr [3:0] $end
$var wire 1 , wrst_n $end
$var wire 1 ! wfull $end
$var wire 4 K wbnext [3:0] $end
$var parameter 32 L ADDR_WD $end
$var reg 4 M wbin_r [3:0] $end
$var reg 4 N wgray_r [3:0] $end
$var reg 1 O wq1_r $end
$var reg 1 ! wq2_r $end
$upscope $end
$upscope $end
$upscope $end
$enddefinitions $end
$comment Show the parameter values. $end
$dumpall
b100 L
b100 E
b10000 A
b1000 @
b100 ?
b100 9
b1000 4
b100 3
b1000 %
b100 $
$end
#0
$dumpvars
0O
b0 N
b0 M
b1 K
b0 J
b1 I
0H
b0 G
b0 F
b1 D
b0 C
b1 B
b0 >
b0 =
bx <
bx ;
0:
b0 8
b0 7
16
05
02
11
bx 0
b0 /
b0 .
bx -
0,
1+
bx *
0)
0(
1'
0&
bx #
0"
0!
$end
#2
15
1(
1,
#3
12
b11 I
b10 K
b1 M
b1 .
b1 7
b1 =
b1 J
b1 N
1)
#5
b100100 *
b100100 -
b100100 <
#6
1H
1"
02
b1 B
b1 D
b1 F
b1 /
b1 8
b1 >
b1 C
b1 G
0)
1&
#9
12
b10 I
b100100 #
b100100 0
b100100 ;
b11 K
b10 M
b11 .
b11 7
b11 =
b11 J
b11 N
1)
#10
b1 *
b1 -
b1 <
#12
0)
0&
#15
b110 I
b100 K
b11 M
b10 .
b10 7
b10 =
b10 J
b10 N
1)
b1001 *
b1001 -
b1001 <
#18
0H
0)
1&
#20
b1100011 *
b1100011 -
b1100011 <
#21
05
b111 I
b101 K
b100 M
b110 .
b110 7
b110 =
b110 J
b110 N
1)
#24
0)
0&
#25
b1101 *
b1101 -
b1101 <
#27
b101 I
b110 K
b101 M
b111 .
b111 7
b111 =
b111 J
b111 N
1)
#30
b11 B
b10 D
0"
0)
1&
#33
b100 I
b111 K
b110 M
b101 .
b101 7
b101 =
b101 J
b101 N
1)
#35
b1100101 *
b1100101 -
b1100101 <
#36
0)
0&
#39
b1100 I
b1000 K
b111 M
b100 .
b100 7
b100 =
b100 J
b100 N
1)
#40
b10010 *
b10010 -
b10010 <
#42
b10 B
b11 D
b10 F
b1001 #
b1001 0
b1001 ;
b11 /
b11 8
b11 >
b11 C
b11 G
0)
1&
#45
15
b1101 I
b1001 K
b1000 M
b1100 .
b1100 7
b1100 =
b1100 J
b1100 N
1)
b1 *
b1 -
b1 <
#48
0)
0&
#50
b1101 *
b1101 -
b1101 <
#51
b1111 I
b1010 K
b1001 M
b1101 .
b1101 7
b1101 =
b1101 J
b1101 N
1)
#54
b110 B
b100 D
b11 F
b1100011 #
b1100011 0
b1100011 ;
b10 /
b10 8
b10 >
b10 C
b10 G
0)
1&
#55
b1110110 *
b1110110 -
b1110110 <
#57
b1110 I
b1011 K
b1010 M
b1111 .
b1111 7
b1111 =
b1111 J
b1111 N
1)
#60
0)
b111101 *
b111101 -
b111101 <
0&
#63
b1010 I
b1100 K
b1011 M
b1110 .
b1110 7
b1110 =
b1110 J
b1110 N
1)
#65
b1101101 *
b1101101 -
b1101101 <
#66
05
b111 B
b101 D
b100 F
b1101 #
b1101 0
b1101 ;
b110 /
b110 8
b110 >
b110 C
b110 G
0)
1&
#69
15
b1011 I
b1101 K
b1100 M
b1010 .
b1010 7
b1010 =
b1010 J
b1010 N
1)
#70
b1100 *
b1100 -
b1100 <
#72
0)
0&
#75
b1001 I
b1110 K
b1101 M
b1011 .
b1011 7
b1011 =
b1011 J
b1011 N
1)
b1111001 *
b1111001 -
b1111001 <
#78
b101 B
b110 D
b101 F
b111 /
b111 8
b111 >
b111 C
b111 G
0)
1&
#80
b1000110 *
b1000110 -
b1000110 <
#81
b1000 I
b1111 K
b1110 M
b1001 .
b1001 7
b1001 =
b1001 J
b1001 N
1)
#84
0)
0&
#85
b1000101 *
b1000101 -
b1000101 <
#87
b0 I
b0 K
b1111 M
b1000 .
b1000 7
b1000 =
b1000 J
b1000 N
1)
#90
b100 B
b111 D
b110 F
b1100101 #
b1100101 0
b1100101 ;
b101 /
b101 8
b101 >
b101 C
b101 G
0)
b101010 *
b101010 -
b101010 <
1&
#93
1:
06
b1 I
b1 K
b0 M
b0 .
b0 7
b0 =
b0 J
b0 N
1)
#95
b1100101 *
b1100101 -
b1100101 <
#96
0)
0&
#99
b11 I
b10 K
b1 M
b1 .
b1 7
b1 =
b1 J
b1 N
1)
#100
b1110111 *
b1110111 -
b1110111 <
#102
b1100 B
b1000 D
b111 F
b1 #
b1 0
b1 ;
b100 /
b100 8
b100 >
b100 C
b100 G
0)
1&
#105
b10 I
b11 K
b10 M
b11 .
b11 7
b11 =
b11 J
b11 N
1)
b10010 *
b10010 -
b10010 <
#108
0)
0&
#110
b1111 *
b1111 -
b1111 <
#111
b110 I
b100 K
b11 M
b10 .
b10 7
b10 =
b10 J
b10 N
1)
#114
16
b1101 B
b1001 D
b1000 F
b1101 #
b1101 0
b1101 ;
b1100 /
b1100 8
b1100 >
b1100 C
b1100 G
0)
1&
#115
b1110010 *
b1110010 -
b1110010 <
#117
06
b111 I
b101 K
b100 M
b110 .
b110 7
b110 =
b110 J
b110 N
1)
#120
0)
b1001110 *
b1001110 -
b1001110 <
0&
#123
b101 I
b110 K
b101 M
b111 .
b111 7
b111 =
b111 J
b111 N
1)
#125
b1101000 *
b1101000 -
b1101000 <
#126
b1111 B
b1010 D
b1001 F
b1110110 #
b1110110 0
b1110110 ;
b1101 /
b1101 8
b1101 >
b1101 C
b1101 G
0)
1&
#129
b100 I
b111 K
b110 M
b101 .
b101 7
b101 =
b101 J
b101 N
1)
#130
b1000101 *
b1000101 -
b1000101 <
#132
0)
0&
#135
b1100 I
b1000 K
b111 M
b100 .
b100 7
b100 =
b100 J
b100 N
1)
b1011100 *
b1011100 -
b1011100 <
#138
b1110 B
b1011 D
b1010 F
b111101 #
b111101 0
b111101 ;
b1111 /
b1111 8
b1111 >
b1111 C
b1111 G
0)
1&
#140
b111101 *
b111101 -
b111101 <
#141
16
b1101 I
b1001 K
b1000 M
b1100 .
b1100 7
b1100 =
b1100 J
b1100 N
1)
#144
0)
0&
#145
b101101 *
b101101 -
b101101 <
#147
b1111 I
b1010 K
b1001 M
b1101 .
b1101 7
b1101 =
b1101 J
b1101 N
1)
#150
b1010 B
b1100 D
b1011 F
b1101101 #
b1101101 0
b1101101 ;
b1110 /
b1110 8
b1110 >
b1110 C
b1110 G
0)
b1100101 *
b1100101 -
b1100101 <
1&
#153
b1110 I
b1011 K
b1010 M
b1111 .
b1111 7
b1111 =
b1111 J
b1111 N
1)
#155
b1100011 *
b1100011 -
b1100011 <
#156
0)
0&
#159
1O
1!
01
b1110 I
b1011 K
b1011 M
b1110 .
b1110 7
b1110 =
b1110 J
b1110 N
1)
#160
b1010 *
b1010 -
b1010 <
#162
06
11
b1011 B
b1101 D
b1100 F
b1111001 #
b1111001 0
b1111001 ;
b1010 /
b1010 8
b1010 >
b1010 C
b1010 G
0)
1&
#165
0O
1)
b0 *
b0 -
b0 <
#168
0)
0&
#170
b100000 *
b100000 -
b100000 <
#171
b1010 I
b1100 K
0!
1)
#174
b1001 B
b1110 D
b1101 F
b1000110 #
b1000110 0
b1000110 ;
b1011 /
b1011 8
b1011 >
b1011 C
b1011 G
0)
1&
#175
b101010 *
b101010 -
b101010 <
#177
16
b1011 I
b1101 K
b1100 M
b1010 .
b1010 7
b1010 =
b1010 J
b1010 N
1)
#180
0)
b11101 *
b11101 -
b11101 <
0&
#183
1O
1!
01
b1011 I
b1101 K
b1101 M
b1011 .
b1011 7
b1011 =
b1011 J
b1011 N
1)
#185
b10110 *
b10110 -
b10110 <
#186
11
b1000 B
b1111 D
b1110 F
b1000101 #
b1000101 0
b1000101 ;
b1001 /
b1001 8
b1001 >
b1001 C
b1001 G
0)
1&
#189
0O
1)
#190
b10011 *
b10011 -
b10011 <
#192
0)
0&
#195
b1001 I
b1110 K
0!
1)
b1101 *
b1101 -
b1101 <
#198
b0 B
b0 D
b1111 F
b101010 #
b101010 0
b101010 ;
b1000 /
b1000 8
b1000 >
b1000 C
b1000 G
0)
1&
#200
b1010011 *
b1010011 -
b1010011 <
#201
b1000 I
b1111 K
b1110 M
b1001 .
b1001 7
b1001 =
b1001 J
b1001 N
1)
#204
0)
0&
#205
b1101011 *
b1101011 -
b1101011 <
#207
1O
1!
01
b1000 I
b1111 K
b1111 M
b1000 .
b1000 7
b1000 =
b1000 J
b1000 N
1)
#210
06
11
b1 B
b1 D
b0 F
b1100101 #
b1100101 0
b1100101 ;
b0 /
b0 8
b0 >
b0 C
b0 G
0)
b1010101 *
b1010101 -
b1010101 <
1&
#213
0O
1)
#215
b10 *
b10 -
b10 <
#216
0)
0&
#219
b0 I
b0 K
0!
1)
#220
b101110 *
b101110 -
b101110 <
#222
b11 B
b10 D
b1 F
b10010 #
b10010 0
b10010 ;
b1 /
b1 8
b1 >
b1 C
b1 G
0)
1&
#225
16
b1 I
b1 K
b0 M
b0 .
b0 7
b0 =
b0 J
b0 N
1)
b11101 *
b11101 -
b11101 <
#228
0)
0&
#230
b1001111 *
b1001111 -
b1001111 <
#231
1O
1!
01
b1 I
b1 K
b1 M
b1 .
b1 7
b1 =
b1 J
b1 N
1)
#234
11
b10 B
b11 D
b10 F
b1111 #
b1111 0
b1111 ;
b11 /
b11 8
b11 >
b11 C
b11 G
0)
1&
#235
b100011 *
b100011 -
b100011 <
#237
0O
1)
#240
0)
b1010 *
b1010 -
b1010 <
0&
#243
b11 I
b10 K
0!
1)
#245
b1001010 *
b1001010 -
b1001010 <
#246
b110 B
b100 D
b11 F
b1110010 #
b1110010 0
b1110010 ;
b10 /
b10 8
b10 >
b10 C
b10 G
0)
1&
#249
b10 I
b11 K
b10 M
b11 .
b11 7
b11 =
b11 J
b11 N
1)
#250
b111100 *
b111100 -
b111100 <
#252
0)
0&
#255
1O
1!
01
b10 I
b11 K
b11 M
b10 .
b10 7
b10 =
b10 J
b10 N
1)
b1110010 *
b1110010 -
b1110010 <
#258
06
11
b111 B
b101 D
b100 F
b1001110 #
b1001110 0
b1001110 ;
b110 /
b110 8
b110 >
b110 C
b110 G
0)
1&
#260
b1010 *
b1010 -
b1010 <
#261
0O
1)
#264
0)
0&
#265
b1000001 *
b1000001 -
b1000001 <
#267
b110 I
b100 K
0!
1)
#270
b101 B
b110 D
b101 F
b1101000 #
b1101000 0
b1101000 ;
b111 /
b111 8
b111 >
b111 C
b111 G
0)
b1011000 *
b1011000 -
b1011000 <
1&
#273
16
b111 I
b101 K
b100 M
b110 .
b110 7
b110 =
b110 J
b110 N
1)
#275
b1111000 *
b1111000 -
b1111000 <
#276
0)
0&
#279
1O
1!
01
b111 I
b101 K
b101 M
b111 .
b111 7
b111 =
b111 J
b111 N
1)
#280
b1001 *
b1001 -
b1001 <
#282
11
b100 B
b111 D
b110 F
b1011100 #
b1011100 0
b1011100 ;
b101 /
b101 8
b101 >
b101 C
b101 G
0)
1&
#285
0O
1)
b1101011 *
b1101011 -
b1101011 <
#288
0)
0&
#290
b110110 *
b110110 -
b110110 <
#291
b101 I
b110 K
0!
1)
#294
b1100 B
b1000 D
b111 F
b111101 #
b111101 0
b111101 ;
b100 /
b100 8
b100 >
b100 C
b100 G
0)
1&
#295
b1000110 *
b1000110 -
b1000110 <
#297
b100 I
b111 K
b110 M
b101 .
b101 7
b101 =
b101 J
b101 N
1)
#300
0)
b101110 *
b101110 -
b101110 <
0&
#303
1O
1!
01
b100 I
b111 K
b111 M
b100 .
b100 7
b100 =
b100 J
b100 N
1)
#305
b111100 *
b111100 -
b111100 <
#306
06
11
b1101 B
b1001 D
b1000 F
b101101 #
b101101 0
b101101 ;
b1100 /
b1100 8
b1100 >
b1100 C
b1100 G
0)
1&
#309
0O
1)
#310
b101010 *
b101010 -
b101010 <
#312
0)
0&
#315
b1100 I
b1000 K
0!
1)
b1011 *
b1011 -
b1011 <
#318
b1111 B
b1010 D
b1001 F
b1100101 #
b1100101 0
b1100101 ;
b1101 /
b1101 8
b1101 >
b1101 C
b1101 G
0)
1&
#320
b1110001 *
b1110001 -
b1110001 <
#321
16
b1101 I
b1001 K
b1000 M
b1100 .
b1100 7
b1100 =
b1100 J
b1100 N
1)
#324
0)
0&
#325
b101 *
b101 -
b101 <
#327
1O
1!
01
b1101 I
b1001 K
b1001 M
b1101 .
b1101 7
b1101 =
b1101 J
b1101 N
1)
#330
11
b1110 B
b1011 D
b1010 F
b1100011 #
b1100011 0
b1100011 ;
b1111 /
b1111 8
b1111 >
b1111 C
b1111 G
0)
b1001111 *
b1001111 -
b1001111 <
1&
#333
0O
1)
#335
b111011 *
b111011 -
b111011 <
#336
0)
0&
#339
b1111 I
b1010 K
0!
1)
#340
b111010 *
b111010 -
b111010 <
#342
b1010 B
b1100 D
b1011 F
b101010 #
b101010 0
b101010 ;
b1110 /
b1110 8
b1110 >
b1110 C
b1110 G
0)
1&
#345
b1110 I
b1011 K
b1010 M
b1111 .
b1111 7
b1111 =
b1111 J
b1111 N
1)
b1111110 *
b1111110 -
b1111110 <
#348
0)
0&
#350
b10101 *
b10101 -
b10101 <
#351
1O
1!
01
b1110 I
b1011 K
b1011 M
b1110 .
b1110 7
b1110 =
b1110 J
b1110 N
1)
#354
06
11
b1011 B
b1101 D
b1100 F
b11101 #
b11101 0
b11101 ;
b1010 /
b1010 8
b1010 >
b1010 C
b1010 G
0)
1&
#355
b1110001 *
b1110001 -
b1110001 <
#357
0O
1)
#360
0)
b1011001 *
b1011001 -
b1011001 <
0&
#363
b1010 I
b1100 K
0!
1)
#365
b1100010 *
b1100010 -
b1100010 <
#366
b1001 B
b1110 D
b1101 F
b1010011 #
b1010011 0
b1010011 ;
b1011 /
b1011 8
b1011 >
b1011 C
b1011 G
0)
1&
#369
16
b1011 I
b1101 K
b1100 M
b1010 .
b1010 7
b1010 =
b1010 J
b1010 N
1)
#370
b1001100 *
b1001100 -
b1001100 <
#372
0)
0&
#375
1O
1!
01
b1011 I
b1101 K
b1101 M
b1011 .
b1011 7
b1011 =
b1011 J
b1011 N
1)
b11111 *
b11111 -
b11111 <
#378
11
b1000 B
b1111 D
b1110 F
b1101011 #
b1101011 0
b1101011 ;
b1001 /
b1001 8
b1001 >
b1001 C
b1001 G
0)
1&
#380
b1111 *
b1111 -
b1111 <
#381
0O
1)
#384
0)
0&
#385
b1111000 *
b1111000 -
b1111000 <
#387
b1001 I
b1110 K
0!
1)
#390
b0 B
b0 D
b1111 F
b11101 #
b11101 0
b11101 ;
b1000 /
b1000 8
b1000 >
b1000 C
b1000 G
0)
b110111 *
b110111 -
b110111 <
1&
#393
b1000 I
b1111 K
b1110 M
b1001 .
b1001 7
b1001 =
b1001 J
b1001 N
1)
#395
b11111 *
b11111 -
b11111 <
#396
0)
0&
#399
1O
1!
01
b1000 I
b1111 K
b1111 M
b1000 .
b1000 7
b1000 =
b1000 J
b1000 N
1)
#400
b1011100 *
b1011100 -
b1011100 <
#402
06
11
b1 B
b1 D
b0 F
b1001111 #
b1001111 0
b1001111 ;
b0 /
b0 8
b0 >
b0 C
b0 G
0)
1&
